{
  "title": "I Quit Corporate Tech at 33: The Beautiful Reality of My First Year in FIRE",
  "subtitle": "An unfiltered reflection on the first 365 days outside the corporate matrix.",
  "description": "What does the first year of FIRE actually look like? Reflections on escaping the corporate tech bubble, building health, and finding purpose after retiring early at 33.",
  "date": "2026-04-09",
  "cover": "cover.png",
  "tags": [
    "FIRE Journey",
    "Personal Finance",
    "Life After F.i.R.E."
  ],
  "featured": true
}
